hubstore/.private
hubstore/LICENSE
hubstore/__init__.py
hubstore/__main__.py
hubstore/asset/default_cover.png
hubstore/asset/default_hubstore_tile_img.png
hubstore/core/__init__.py
hubstore/hooking/__init__.py
hubstore/hooking/ante_build_hook.py
hubstore/hooking/ante_release_hook.py
hubstore/hooking/post_build_hook.py
hubstore/hooking/post_release_hook.py
hubstore/host/__init__.py
hubstore/host/constants.py
hubstore/host/core.py
hubstore/host/main_host.py
hubstore/misc/__init__.py
hubstore/misc/constant.py
hubstore/misc/default.png
hubstore/misc/funcs.py
hubstore/misc/my_theme.py
hubstore/misc/theme.py
hubstore/misc/default_json/default_apps_list_data.json
hubstore/misc/default_json/default_shared_data.json
hubstore/pyrustic_data/build_report.json
hubstore/pyrustic_data/hooking.json
hubstore/pyrustic_data/hubstore.json
hubstore/pyrustic_data/release_info.json
hubstore/pyrustic_data/backstage/config/build.json
hubstore/pyrustic_data/backstage/config/init.json
hubstore/pyrustic_data/backstage/config/release.json
hubstore/pyrustic_data/backstage/data/build_report.json
hubstore/pyrustic_data/backstage/data/github_release_form.json
hubstore/pyrustic_data/backstage/hooking/build.json
hubstore/pyrustic_data/backstage/hooking/init.json
hubstore/pyrustic_data/backstage/hooking/release.json
hubstore/pyrustic_data/backstage/report/build_report.json
hubstore/pyrustic_data/backstage/report/release_report.json
hubstore/pyrustic_data/hubstore/img.json
hubstore/pyrustic_data/hubstore/promotion.json
hubstore/view/__init__.py
hubstore/view/about.py
hubstore/view/about_view.py
hubstore/view/app_info_view.py
hubstore/view/auth_view.py
hubstore/view/central_view.py
hubstore/view/downloader_view.py
hubstore/view/exception_view.py
hubstore/view/footer_view.py
hubstore/view/header_view.py
hubstore/view/import_list_view.py
hubstore/view/info.py
hubstore/view/init_view.py
hubstore/view/installer.py
hubstore/view/main.py
hubstore/view/main_view.py
hubstore/view/openlist.py
hubstore-0.1.4.dist-info/LICENSE
hubstore-0.1.4.dist-info/METADATA
hubstore-0.1.4.dist-info/WHEEL
hubstore-0.1.4.dist-info/entry_points.txt
hubstore-0.1.4.dist-info/top_level.txt
hubstore-0.1.4.dist-info/RECORD
