Metadata-Version: 2.1
Name: hubstore
Version: 0.1.4
Summary: To Connect Apps With Users
Home-page: https://github.com/pyrustic/hubstore
Author: Pyrustic Evangelist
Author-email: rusticalex@yahoo.com
Maintainer: Pyrustic Evangelist
Maintainer-email: rusticalex@yahoo.com
License: MIT
Keywords: application-store,software-management,software-distribution,desktop-application,wheel-compatible,pyrustic,promotion,peer-to-peer
Platform: UNKNOWN
Classifier: Programming Language :: Python :: 3
Classifier: License :: OSI Approved :: MIT License
Classifier: Operating System :: OS Independent
Requires-Python: >=3.5
License-File: LICENSE
Requires-Dist: tkf
